concopilot_examples/__init__.py
concopilot_examples/cerebrum/__init__.py
concopilot_examples/cerebrum/glmcerebrum/__init__.py
concopilot_examples/cerebrum/glmcerebrum/glmcerebrum.py
concopilot_examples/cerebrum/openaicerebrum/__init__.py
concopilot_examples/cerebrum/openaicerebrum/openaicerebrum.py
concopilot_examples/cerebrum/rwkvcerebrum/__init__.py
concopilot_examples/cerebrum/rwkvcerebrum/rwkvcerebrum.py
concopilot_examples/cerebrum/zhipuaicerebrum/__init__.py
concopilot_examples/cerebrum/zhipuaicerebrum/zhipuaicerebrum.py
concopilot_examples/interactor/__init__.py
concopilot_examples/interactor/auto/__init__.py
concopilot_examples/interactor/auto/interactor.py
concopilot_examples/interactor/chat/__init__.py
concopilot_examples/interactor/chat/interactor.py
concopilot_examples/interactor/chatwithtool/__init__.py
concopilot_examples/interactor/chatwithtool/interactor.py
concopilot_examples/interface/__init__.py
concopilot_examples/interface/chat/__init__.py
concopilot_examples/interface/chat/webchat/__init__.py
concopilot_examples/interface/chat/webchat/interface.py
concopilot_examples/plugin/__init__.py
concopilot_examples/plugin/duckduckgosearch/__init__.py
concopilot_examples/plugin/duckduckgosearch/duckduckgosearch.py
concopilot_examples/plugin/image/__init__.py
concopilot_examples/plugin/image/cropper/__init__.py
concopilot_examples/plugin/image/cropper/cropper.py
concopilot_examples/plugin/modelscope/__init__.py
concopilot_examples/plugin/modelscope/card_detection_correction/__init__.py
concopilot_examples/plugin/modelscope/card_detection_correction/card_detection_correction.py
concopilot_examples/plugin/modelscope/ocr_detection/__init__.py
concopilot_examples/plugin/modelscope/ocr_detection/ocr_detection.py
concopilot_examples/plugin/modelscope/ocr_recognition/__init__.py
concopilot_examples/plugin/modelscope/ocr_recognition/ocr_recognition.py
concopilot_examples/plugin/promptgenerator/__init__.py
concopilot_examples-0.0.5.dist-info/LICENSE
concopilot_examples-0.0.5.dist-info/METADATA
concopilot_examples-0.0.5.dist-info/WHEEL
concopilot_examples-0.0.5.dist-info/top_level.txt
concopilot_examples-0.0.5.dist-info/RECORD
