Metadata-Version: 2.1
Name: concopilot_examples
Version: 0.0.5
Summary: ConCopilot simple examples.
Author-email: ZHONG Weikun <zhong.weikun@live.com>
Project-URL: Homepage, https://github.com/ConCopilot/concopilot-examples
Project-URL: Bug Tracker, https://github.com/ConCopilot/concopilot-examples/issues
Classifier: Programming Language :: Python :: 3
Classifier: Operating System :: OS Independent
Requires-Python: >=3.8
License-File: LICENSE
Requires-Dist: concopilot >=0.0.5
